LICENSE
MANIFEST.in
README.md
setup.py
geopytool/ArArIsoTope.py
geopytool/BackTrace.py
geopytool/Bar.py
geopytool/Bivariate.py
geopytool/CIA.py
geopytool/CIPW.py
geopytool/Clastic.py
geopytool/Cluster.py
geopytool/Combine.py
geopytool/Combine_Level.py
geopytool/CustomClass.py
geopytool/Dist.py
geopytool/FillNaN.png
geopytool/Flatten.py
geopytool/FluidInclusion.py
geopytool/Frequency.py
geopytool/GLMultiDimension.py
geopytool/Harker.py
geopytool/HarkerDIY.py
geopytool/HarkerOld.py
geopytool/ICA.py
geopytool/ImportDependence.py
geopytool/IsoTope.py
geopytool/Isochronous.py
geopytool/K2OSiO2.py
geopytool/KArIsoTope.py
geopytool/LICENSE
geopytool/L_round_字母l.png
geopytool/MANIFEST
geopytool/MANIFEST.in
geopytool/M_round_字母m.png
geopytool/Magic.py
geopytool/MultiDimension.py
geopytool/MyDT.py
geopytool/MyFA.py
geopytool/MyGAN.py
geopytool/MyHist.py
geopytool/MyLDA.py
geopytool/MyLDA_OLD.py
geopytool/MyMLP.py
geopytool/MyPCA.py
geopytool/MyPCA_middle.py
geopytool/MyQDA.py
geopytool/MyRBM.py
geopytool/NewCIPW.py
geopytool/Niggli.py
geopytool/OldTrace.py
geopytool/P_round_字母p.png
geopytool/Pearce.py
geopytool/Pie.py
geopytool/PlotModel.py
geopytool/QAPF.py
geopytool/QFL.py
geopytool/QmFLt.py
geopytool/README.md
geopytool/REE.py
geopytool/Raman.py
geopytool/RbSrIsoTope.py
geopytool/RemovedTabelViewer.py
geopytool/Rose.py
geopytool/SVM.py
geopytool/Saccani.py
geopytool/SmNdIsoTope.py
geopytool/Sta.py
geopytool/Stereo.py
geopytool/TAS.py
geopytool/TabelViewer.py
geopytool/Temp.py
geopytool/Test.py
geopytool/Testing.py
geopytool/ThreeD.py
geopytool/ThreeD_Vispy.py
geopytool/ThreeD_Vispy.py.back
geopytool/ThreeD_old.py
geopytool/TiAlCaMgMnKNaSi.py
geopytool/Trace.py
geopytool/TraceNew.py
geopytool/Trans.py
geopytool/TwoD.py
geopytool/TwoD_Grey.py
geopytool/XY.py
geopytool/XYZ.py
geopytool/ZirconCe.py
geopytool/ZirconCeOld.py
geopytool/ZrYSrTi.py
geopytool/__init__.py
geopytool/auto.png
geopytool/b.png
geopytool/bar.png
geopytool/calc.png
geopytool/close.png
geopytool.egg-info/PKG-INFO
geopytool.egg-info/SOURCES.txt
geopytool.egg-info/dependency_links.txt
geopytool.egg-info/requires.txt
geopytool.egg-info/top_level.txt