Metadata-Version: 2.1
Name: geopytool
Version: 1.1
Summary: a tool for daily geology related task. visit geopytool.com for further information
Home-page: https://github.com/GeoPyTool/GeoPyTool
Author: cycleuser
Author-email: cycleuser@cycleuser.org
License-File: LICENSE
Requires-Dist: cython
Requires-Dist: numpy
Requires-Dist: pandas
Requires-Dist: scipy
Requires-Dist: xlrd
Requires-Dist: openpyxl
Requires-Dist: matplotlib
Requires-Dist: BeautifulSoup4
Requires-Dist: requests
Requires-Dist: PyQt5
Requires-Dist: scikit-image
Requires-Dist: torch
Requires-Dist: keras
Requires-Dist: tqdm
Requires-Dist: gym
